neutrosophics/__init__.py
neutrosophics/analysis.py
neutrosophics/logic.py
neutrosophics/types.py
neutrosophics/validators.py
neutrosophics-0.0.4.dist-info/METADATA
neutrosophics-0.0.4.dist-info/WHEEL
neutrosophics-0.0.4.dist-info/licenses/LICENCE
neutrosophics-0.0.4.dist-info/RECORD
