Metadata-Version: 2.4
Name: neutrosophics
Version: 0.0.4
Summary: Working with netrosophic sets
Project-URL: Homepage, https://github.com/NozirTukhtamurodov/netrosophic
Project-URL: Issues, https://github.com/NozirTukhtamurodov/netrosophic
Author-email: Mariya Sha <nozir9407@gmail.com>
License-File: LICENCE
Classifier: License :: OSI Approved :: GNU General Public License v3 (GPLv3)
Classifier: Operating System :: OS Independent
Classifier: Programming Language :: Python :: 3
Requires-Python: >=3.6
